{
	"asset": {
		"version": "1.0"
	},
	"geometricError": 1.0825317547305482,
	"root": {
		"children": [
			{
				"content": {
					"uri": "0/tileset.json"
				},
				"boundingVolume": {
					"region": [
						0.2426616925150247,
						0.710994359438932,
						0.24266339038149493,
						0.7109955115703699,
						298.17678125000003,
						300.582921875
					]
				},
				"geometricError": 0.5412658773652741,
				"refine": "ADD"
			},
			{
				"content": {
					"uri": "1/content.pnts"
				},
				"boundingVolume": {
					"region": [
						0.24266339038149493,
						0.710994359438932,
						0.24266508824796512,
						0.7109955115703699,
						298.17678125000003,
						300.582921875
					]
				},
				"geometricError": 0.5412658773652741,
				"refine": "ADD"
			},
			{
				"content": {
					"uri": "2/content.pnts"
				},
				"boundingVolume": {
					"region": [
						0.2426616925150247,
						0.7109955115703699,
						0.24266339038149493,
						0.710996663700656,
						298.17678125000003,
						300.582921875
					]
				},
				"geometricError": 0.5412658773652741,
				"refine": "ADD"
			},
			{
				"content": {
					"uri": "3/tileset.json"
				},
				"boundingVolume": {
					"region": [
						0.24266339038149493,
						0.7109955115703699,
						0.24266508824796512,
						0.710996663700656,
						298.17678125000003,
						300.582921875
					]
				},
				"geometricError": 0.5412658773652741,
				"refine": "ADD"
			}
		],
		"content": {
			"uri": "content.pnts"
		},
		"boundingVolume": {
			"region": [
				0.2426616925150247,
				0.710994359438932,
				0.24266508824796512,
				0.710996663700656,
				298.17678125000003,
				302.98906250000005
			]
		},
		"geometricError": 1.0825317547305482,
		"refine": "ADD"
	}
}